<?xml version="1.0" encoding="utf-8" ?>
<dwsync>
<file name="autoload.php" server="dev.iworkaudit.com//iwadevuk/" local="130371208615883583" remote="130382565600000000" Dst="1" />
<file name="config.php" server="dev.iworkaudit.com//iwadevuk/" local="130371208615933586" remote="130382565600000000" Dst="1" />
<file name="constants.php" server="dev.iworkaudit.com//iwadevuk/" local="130371208615963587" remote="130382565600000000" Dst="1" />
<file name="database.php" server="dev.iworkaudit.com//iwadevuk/" local="130371208615993589" remote="130382565600000000" Dst="1" />
<file name="doctypes.php" server="dev.iworkaudit.com//iwadevuk/" local="130371208616153598" remote="130382565600000000" Dst="1" />
<file name="foreign_chars.php" server="dev.iworkaudit.com//iwadevuk/" local="130371208616153598" remote="130382565600000000" Dst="1" />
<file name="hooks.php" server="dev.iworkaudit.com//iwadevuk/" local="130371208616183600" remote="130382565600000000" Dst="1" />
<file name="index.html" server="dev.iworkaudit.com//iwadevuk/" local="130371208616193600" remote="130382565600000000" Dst="1" />
<file name="migration.php" server="dev.iworkaudit.com//iwadevuk/" local="130371208616233603" remote="130382565600000000" Dst="1" />
<file name="mimes.php" server="dev.iworkaudit.com//iwadevuk/" local="130371208616273605" remote="130382565600000000" Dst="1" />
<file name="profiler.php" server="dev.iworkaudit.com//iwadevuk/" local="130371208616303607" remote="130382565600000000" Dst="1" />
<file name="routes.php" server="dev.iworkaudit.com//iwadevuk/" local="130371208616333608" remote="130382565600000000" Dst="1" />
<file name="smileys.php" server="dev.iworkaudit.com//iwadevuk/" local="130371208616333608" remote="130382565600000000" Dst="1" />
<file name="user_agents.php" server="dev.iworkaudit.com//iwadevuk/" local="130371208616343609" remote="130382565600000000" Dst="1" />
</dwsync>